gemseo_fmu/__init__.py
gemseo_fmu/disciplines/__init__.py
gemseo_fmu/disciplines/_variables.py
gemseo_fmu/disciplines/base_fmu_discipline.py
gemseo_fmu/disciplines/do_step_fmu_discipline.py
gemseo_fmu/disciplines/dynamic_fmu_discipline.py
gemseo_fmu/disciplines/fmu_discipline.py
gemseo_fmu/disciplines/static_fmu_discipline.py
gemseo_fmu/disciplines/time_series.py
gemseo_fmu/disciplines/time_stepping_system.py
gemseo_fmu/problems/__init__.py
gemseo_fmu/problems/fmu_files/__init__.py
gemseo_fmu/problems/fmu_files/linux/FMU3Model.fmu
gemseo_fmu/problems/fmu_files/linux/MassSpringSubSystem1.fmu
gemseo_fmu/problems/fmu_files/linux/MassSpringSubSystem2.fmu
gemseo_fmu/problems/fmu_files/linux/MassSpringSystem.fmu
gemseo_fmu/problems/fmu_files/linux/Mass_Damper.fmu
gemseo_fmu/problems/fmu_files/linux/add.fmu
gemseo_fmu/problems/fmu_files/linux/ramp.fmu
gemseo_fmu/problems/fmu_files/win32/FMU3Model.fmu
gemseo_fmu/problems/fmu_files/win32/MassSpringSubSystem1.fmu
gemseo_fmu/problems/fmu_files/win32/MassSpringSubSystem2.fmu
gemseo_fmu/problems/fmu_files/win32/MassSpringSystem.fmu
gemseo_fmu/problems/fmu_files/win32/Mass_Damper.fmu
gemseo_fmu/problems/fmu_files/win32/add.fmu
gemseo_fmu/problems/fmu_files/win32/ramp.fmu
gemseo_fmu/utils/__init__.py
gemseo_fmu/utils/plotting.py
gemseo_fmu/utils/time_duration.py
gemseo_fmu/utils/time_manager.py
gemseo_fmu/utils/time_series.py
gemseo_fmu-3.1.1.dist-info/licenses/LICENSE.txt
gemseo_fmu-3.1.1.dist-info/METADATA
gemseo_fmu-3.1.1.dist-info/WHEEL
gemseo_fmu-3.1.1.dist-info/entry_points.txt
gemseo_fmu-3.1.1.dist-info/top_level.txt
gemseo_fmu-3.1.1.dist-info/RECORD
